{
  "element": {
    "sourceTag": "container",
    "type": "custom",
    "children": [
      {
        "sourceTag": "text",
        "type": "custom",
        "children": [
          "PAUSED"
        ],
        "properties": {
          "fontsize": "14",
          "fontweight": "bold",
          "color": "#ffdd44"
        },
        "dataUid": "uid-2"
      },
      {
        "sourceTag": "container",
        "type": "custom",
        "children": [
          {
            "sourceTag": "text",
            "type": "custom",
            "children": [
              "RESUME"
            ],
            "properties": {
              "name": "btn-resume",
              "fontsize": "10",
              "color": "#44ff44",
              "backgroundcolor": "#003300",
              "padding": "6",
              "borderradius": "3",
              "bordercolor": "#44ff44",
              "borderwidth": "1",
              "cursor": "pointer"
            },
            "dataUid": "uid-4"
          },
          {
            "sourceTag": "text",
            "type": "custom",
            "children": [
              "QUIT"
            ],
            "properties": {
              "name": "btn-quit",
              "fontsize": "10",
              "color": "#ff4444",
              "backgroundcolor": "#330000",
              "padding": "6",
              "borderradius": "3",
              "bordercolor": "#ff4444",
              "borderwidth": "1",
              "cursor": "pointer"
            },
            "dataUid": "uid-5"
          }
        ],
        "properties": {
          "flexdirection": "column",
          "gap": "6",
          "alignitems": "center",
          "margintop": "8"
        },
        "dataUid": "uid-3"
      }
    ],
    "properties": {
      "name": "root",
      "flexdirection": "column",
      "alignitems": "center",
      "gap": "8",
      "padding": "12"
    },
    "dataUid": "uid-1"
  },
  "classes": {},
  "ranges": {
    "uid-1": {
      "start": {
        "line": 0,
        "column": 0
      },
      "end": {
        "line": 6,
        "column": 12
      }
    },
    "uid-2": {
      "start": {
        "line": 1,
        "column": 2
      },
      "end": {
        "line": 1,
        "column": 69
      }
    },
    "uid-3": {
      "start": {
        "line": 2,
        "column": 2
      },
      "end": {
        "line": 5,
        "column": 14
      }
    },
    "uid-4": {
      "start": {
        "line": 3,
        "column": 4
      },
      "end": {
        "line": 3,
        "column": 181
      }
    },
    "uid-5": {
      "start": {
        "line": 4,
        "column": 4
      },
      "end": {
        "line": 4,
        "column": 177
      }
    }
  }
}